package_name_exporter/__init__.py
package_name_exporter/exporter.py
package_name_exporter-0.0.0.dist-info/LICENSE
package_name_exporter-0.0.0.dist-info/METADATA
package_name_exporter-0.0.0.dist-info/WHEEL
package_name_exporter-0.0.0.dist-info/top_level.txt
package_name_exporter-0.0.0.dist-info/RECORD
