Metadata-Version: 2.1
Name: package-name-exporter
Version: 0.0.0
Summary: Export python packages installed to txt, pdf and xls format
Home-page: https://github.com/Allwin12/package-name-exporter
Author: Allwin Raju
Author-email: allwindicaprio@gmail.com
License: UNKNOWN
Platform: UNKNOWN
Classifier: Programming Language :: Python :: 3
Classifier: License :: OSI Approved :: MIT License
Classifier: Operating System :: OS Independent
Requires-Python: >=3.6
Requires-Dist: xlwt (>=1.3)
Requires-Dist: fpdf (>=1.7)
